bstpp/__init__.py
bstpp/inference_functions.py
bstpp/main.py
bstpp/trigger.py
bstpp/utils.py
bstpp/vae_functions.py
bstpp/data/BH_conflicts.csv
bstpp/data/BH_cov.csv
bstpp/data/Boundaries - Community Areas (current).zip
bstpp/data/Chicago_2022_xyt.csv
bstpp/data/Chicago_2023_xyt.csv
bstpp/data/Chicago_cov.zip
bstpp/data/__init__.py
bstpp/decoders/2d_decoder.pkl
bstpp/decoders/2d_decoder_10_5.pkl
bstpp/decoders/2d_decoder_12.pkl
bstpp/decoders/2d_decoder_15_5_large.pkl
bstpp/decoders/2d_decoder_15_5_large_device.pkl
bstpp/decoders/2d_decoder_fixvar.pkl
bstpp/decoders/__init__.py
bstpp/decoders/decoder_1d_T50_fixed_ls
bstpp/decoders/decoder_1d_T50_fixed_ls10
bstpp/decoders/decoder_1d_T50_fixed_ls_n900
bstpp/decoders/decoder_1d_T80_fixed_ls10
bstpp/decoders/decoder_1d_n400_integral_n
bstpp/decoders/decoder_1d_n400_lgcp
bstpp/decoders/decoder_2d_n25_infer_hyperpars
bstpp/decoders/decoders
BSTPP-0.1.1.dist-info/LICENSE.txt
BSTPP-0.1.1.dist-info/METADATA
BSTPP-0.1.1.dist-info/WHEEL
BSTPP-0.1.1.dist-info/top_level.txt
BSTPP-0.1.1.dist-info/RECORD
