Metadata-Version: 2.1
Name: BSTPP
Version: 0.1.1
Summary: Bayesian Spatiotemporal Point Process
Home-page: https://github.com/imanring/BSTPP.git
Author: Isaac Manring
Author-email: isaacamanring@gmail.com
License: MIT
License-File: LICENSE.txt
Requires-Dist: dill >=0.3.5.1
Requires-Dist: geopandas >=0.14.0
Requires-Dist: importlib-resources
Requires-Dist: jax ==0.4.23
Requires-Dist: jaxlib ==0.4.23
Requires-Dist: matplotlib >=3.5.2
Requires-Dist: multipledispatch >=0.6.0
Requires-Dist: numpy >=1.24.1
Requires-Dist: numpyro >=0.10.0
Requires-Dist: opt-einsum >=3.3.0
Requires-Dist: packaging >=21.3
Requires-Dist: pandas >=1.4.3
Requires-Dist: pyparsing >=3.0.9
Requires-Dist: scipy >=1.9.0
Requires-Dist: six >=1.16.0
Requires-Dist: tqdm >=4.64.0
